{
  "id": "4a295a05ea9d",
  "formType": "commercial",
  "fieldId": "reconciliation",
  "propertyType": "residential",
  "marketType": "suburban",
  "marketArea": "",
  "sourceType": "imported",
  "qualityScore": 70,
  "tags": [],
  "text": "Based on the analysis and conclusions presented in the attached report, my opinion of the market value of the fee simple interest in the subject property, in its current “as is” condition, as of February 16, 2026, is $670,000. The value conclusion represents the market value of the subject property in 'as-is' condition. All planned renovations are completed in a professional manner and in accordance with typical market standards.",
  "createdAt": "2026-03-07T21:05:39.750Z",
  "updatedAt": "2026-03-07T21:05:39.750Z"
}